{
  "displayFieldName" : "",
  "fieldAliases" : {
    "FID" : "FID",
    "PMNTN_SN" : "PMNTN_SN",
    "MNTN_CODE" : "MNTN_CODE",
    "MNTN_NM" : "MNTN_NM",
    "PMNTN_NM" : "PMNTN_NM",
    "PMNTN_MAIN" : "PMNTN_MAIN",
    "PMNTN_LT" : "PMNTN_LT",
    "PMNTN_DFFL" : "PMNTN_DFFL",
    "PMNTN_UPPL" : "PMNTN_UPPL",
    "PMNTN_GODN" : "PMNTN_GODN",
    "PMNTN_MTRQ" : "PMNTN_MTRQ",
    "PMNTN_CNRL" : "PMNTN_CNRL",
    "PMNTN_CLS_" : "PMNTN_CLS_",
    "PMNTN_RISK" : "PMNTN_RISK",
    "PMNTN_RECO" : "PMNTN_RECO",
    "DATA_STDR_" : "DATA_STDR_",
    "MNTN_ID" : "MNTN_ID"
  },
  "geometryType" : "esriGeometryPolyline",
  "spatialReference" : {
    "wkt" : "PROJCS[\"PCS_ITRF2000_TM\",GEOGCS[\"GCS_ITRF_2000\",DATUM[\"D_ITRF_2000\",SPHEROID[\"GRS_1980\",6378137.0,298.257222101]],PRIMEM[\"Greenwich\",0.0],UNIT[\"Degree\",0.0174532925199433]],PROJECTION[\"Transverse_Mercator\"],PARAMETER[\"False_Easting\",200000.0],PARAMETER[\"False_Northing\",600000.0],PARAMETER[\"Central_Meridian\",127.0],PARAMETER[\"Scale_Factor\",1.0],PARAMETER[\"Latitude_Of_Origin\",38.0],UNIT[\"Meter\",1.0]]"
  },
  "fields" : [
    {
      "name" : "FID",
      "type" : "esriFieldTypeOID",
      "alias" : "FID"
    },
    {
      "name" : "PMNTN_SN",
      "type" : "esriFieldTypeDouble",
      "alias" : "PMNTN_SN"
    },
    {
      "name" : "MNTN_CODE",
      "type" : "esriFieldTypeString",
      "alias" : "MNTN_CODE",
      "length" : 9
    },
    {
      "name" : "MNTN_NM",
      "type" : "esriFieldTypeString",
      "alias" : "MNTN_NM",
      "length" : 50
    },
    {
      "name" : "PMNTN_NM",
      "type" : "esriFieldTypeString",
      "alias" : "PMNTN_NM",
      "length" : 50
    },
    {
      "name" : "PMNTN_MAIN",
      "type" : "esriFieldTypeString",
      "alias" : "PMNTN_MAIN",
      "length" : 200
    },
    {
      "name" : "PMNTN_LT",
      "type" : "esriFieldTypeSingle",
      "alias" : "PMNTN_LT"
    },
    {
      "name" : "PMNTN_DFFL",
      "type" : "esriFieldTypeString",
      "alias" : "PMNTN_DFFL",
      "length" : 8
    },
    {
      "name" : "PMNTN_UPPL",
      "type" : "esriFieldTypeDouble",
      "alias" : "PMNTN_UPPL"
    },
    {
      "name" : "PMNTN_GODN",
      "type" : "esriFieldTypeDouble",
      "alias" : "PMNTN_GODN"
    },
    {
      "name" : "PMNTN_MTRQ",
      "type" : "esriFieldTypeString",
      "alias" : "PMNTN_MTRQ",
      "length" : 200
    },
    {
      "name" : "PMNTN_CNRL",
      "type" : "esriFieldTypeString",
      "alias" : "PMNTN_CNRL",
      "length" : 1
    },
    {
      "name" : "PMNTN_CLS_",
      "type" : "esriFieldTypeString",
      "alias" : "PMNTN_CLS_",
      "length" : 1
    },
    {
      "name" : "PMNTN_RISK",
      "type" : "esriFieldTypeString",
      "alias" : "PMNTN_RISK",
      "length" : 200
    },
    {
      "name" : "PMNTN_RECO",
      "type" : "esriFieldTypeString",
      "alias" : "PMNTN_RECO",
      "length" : 1
    },
    {
      "name" : "DATA_STDR_",
      "type" : "esriFieldTypeString",
      "alias" : "DATA_STDR_",
      "length" : 10
    },
    {
      "name" : "MNTN_ID",
      "type" : "esriFieldTypeString",
      "alias" : "MNTN_ID",
      "length" : 10
    }
  ],
  "features" : [
    {
      "attributes" : {
        "FID" : 0,
        "PMNTN_SN" : 41508,
        "MNTN_CODE" : "422303401",
        "MNTN_NM" : "울미산",
        "PMNTN_NM" : "고무릉리구간",
        "PMNTN_MAIN" : " ",
        "PMNTN_LT" : 5.29,
        "PMNTN_DFFL" : "쉬움",
        "PMNTN_UPPL" : 93,
        "PMNTN_GODN" : 65,
        "PMNTN_MTRQ" : " ",
        "PMNTN_CNRL" : " ",
        "PMNTN_CLS_" : " ",
        "PMNTN_RISK" : " ",
        "PMNTN_RECO" : " ",
        "DATA_STDR_" : "2016-12-31",
        "MNTN_ID" : "422306001"
      },
      "geometry" : {
        "paths" : [
          [
            [
              378452.7779000001,
              528501.88260000013
            ],
            [
              378494.49830000009,
              528484.81519999914
            ],
            [
              378499.78679999989,
              528482.45140000246
            ],
            [
              378512.56020000018,
              528476.15020000376
            ],
            [
              378518.42819999997,
              528473.48520000279
            ],
            [
              378524.74540000129,
              528471.133100003
            ],
            [
              378530.52950000018,
              528469.64420000277
            ],
            [
              378534.76660000067,
              528468.93820000254
            ],
            [
              378539.14810000081,
              528468.43019999936
            ],
            [
              378543.64410000108,
              528468.12390000001
            ],
            [
              378548.22020000126,
              528468.02150000259
            ],
            [
              378552.84339999966,
              528468.12410000153
            ],
            [
              378557.46930000093,
              528468.43090000004
            ],
            [
              378562.05620000046,
              528468.9392000027
            ],
            [
              378566.5607000012,
              528469.64420000277
            ],
            [
              378572.07139999978,
              528470.77480000071
            ],
            [
              378577.48070000019,
              528472.1612999998
            ],
            [
              378582.7098000003,
              528473.78329999931
            ],
            [
              378587.70200000051,
              528475.6230999995
            ],
            [
              378592.39680000115,
              528477.65699999966
            ],
            [
              378596.7761000013,
              528479.87580000237
            ],
            [
              378600.81290000118,
              528482.26559999958
            ],
            [
              378605.36560000014,
              528485.55770000257
            ],
            [
              378608.79530000221,
              528489.13100000098
            ],
            [
              378611.32309999969,
              528492.62769999914
            ],
            [
              378614.2265999997,
              528497.59770000167
            ],
            [
              378620.48730000015,
              528509.58860000037
            ],
            [
              378623.73840000108,
              528514.72540000267
            ],
            [
              378626.40370000061,
              528517.76139999926
            ],
            [
              378630.08590000123,
              528520.39150000177
            ],
            [
              378634.08969999943,
              528521.59060000256
            ],
            [
              378637.4952000007,
              528521.71299999952
            ],
            [
              378641.29000000004,
              528521.21579999849
            ],
            [
              378645.55050000083,
              528520.08940000087
            ],
            [
              378652.54729999881,
              528517.39060000144
            ],
            [
              378670.48940000124,
              528508.84259999916
            ],
            [
              378674.73460000008,
              528507.02840000205
            ],
            [
              378678.44720000215,
              528505.67540000193
            ],
            [
              378723.96030000132,
              528490.50439999998
            ],
            [
              378756.01589999907,
              528480.27630000003
            ],
            [
              378778.9553000005,
              528473.43690000102
            ],
            [
              378802.90090000071,
              528466.95329999737
            ],
            [
              378830.15760000143,
              528460.16229999997
            ],
            [
              378856.87930000015,
              528453.96570000239
            ],
            [
              378881.35980000068,
              528448.78400000185
            ],
            [
              378911.70190000068,
              528443.0949000027
            ],
            [
              378920.17000000086,
              528441.36460000277
            ],
            [
              378938.88020000048,
              528437.10420000367
            ],
            [
              378946.77390000038,
              528435.5351000037
            ],
            [
              378956.28089999873,
              528434.1557
            ],
            [
              378964.80060000159,
              528433.6129999999
            ],
            [
              378969.6305999998,
              528433.65939999931
            ],
            [
              378974.68439999968,
              528433.95830000192
            ],
            [
              378980.01470000017,
              528434.51250000112
            ],
            [
              378985.72620000225,
              528435.33280000277
            ],
            [
              378995.82150000148,
              528437.20460000075
            ],
            [
              379023.58839999977,
              528443.0949000027
            ],
            [
              379047.05260000005,
              528447.43710000254
            ],
            [
              379061.51600000076,
              528450.68040000089
            ],
            [
              379071.76120000053,
              528453.45480000414
            ],
            [
              379082.13790000137,
              528456.59460000135
            ],
            [
              379092.63450000063,
              528460.09630000219
            ],
            [
              379103.23630000092,
              528463.95500000194
            ],
            [
              379108.21380000003,
              528466.04430000111
            ],
            [
              379113.63889999967,
              528468.71869999915
            ],
            [
              379132.69819999952,
              528479.50029999949
            ],
            [
              379140.45050000027,
              528483.46460000053
            ],
            [
              379144.67410000041,
              528485.28940000013
            ],
            [
              379148.68400000129,
              528486.73920000158
            ],
            [
              379152.55740000028,
              528487.84160000086
            ],
            [
              379156.33499999996,
              528488.60800000094
            ],
            [
              379160.57930000219,
              528489.08910000138
            ],
            [
              379165.36160000227,
              528489.24600000121
            ],
            [
              379183.18300000113,
              528488.49020000175
            ],
            [
              379190.46980000008,
              528488.60800000094
            ],
            [
              379197.58970000129,
              528489.32039999962
            ],
            [
              379205.46140000038,
              528490.54380000196
            ],
            [
              379232.7630000012,
              528496.22919999994
            ],
            [
              379243.56840000115,
              528498.08989999816
            ],
            [
              379258.93300000019,
              528500.68630000204
            ],
            [
              379264.43710000161,
              528501.46839999966
            ],
            [
              379270.45840000082,
              528501.94999999925
            ],
            [
              379275.8069000002,
              528501.88260000013
            ],
            [
              379280.37619999982,
              528501.27740000188
            ],
            [
              379285.36550000124,
              528500.03090000153
            ],
            [
              379290.54540000018,
              528498.2760000024
            ],
            [
              379305.07639999967,
              528492.72709999979
            ],
            [
              379309.6174999997,
              528491.37040000036
            ],
            [
              379313.73450000118,
              528490.50439999998
            ],
            [
              379318.39670000225,
              528489.8673000019
            ],
            [
              379323.27920000069,
              528489.41580000147
            ],
            [
              379333.84990000073,
              528489.05749999918
            ],
            [
              379345.66200000048,
              528489.39730000123
            ],
            [
              379361.14400000032,
              528490.50439999998
            ],
            [
              379375.26669999957,
              528491.68250000104
            ],
            [
              379384.10970000178,
              528492.75310000405
            ],
            [
              379392.07590000052,
              528494.24310000241
            ],
            [
              379399.07160000131,
              528496.19349999912
            ],
            [
              379402.6481999997,
              528497.57789999992
            ],
            [
              379406.45959999971,
              528499.42879999988
            ],
            [
              379410.70220000017,
              528501.83640000038
            ],
            [
              379423.33969999943,
              528509.5446000006
            ],
            [
              379427.4841,
              528511.67460000142
            ],
            [
              379431.31010000035,
              528513.26090000011
            ],
            [
              379437.92680000141,
              528515.3048000019
            ],
            [
              379445.51020000037,
              528517.00440000184
            ],
            [
              379452.89330000151,
              528518.24400000088
            ],
            [
              379471.13410000131,
              528520.84640000202
            ],
            [
              379490.32340000011,
              528524.24300000444
            ],
            [
              379498.62930000015,
              528525.50620000251
            ],
            [
              379507.1297000004,
              528526.35120000131
            ],
            [
              379514.75079999957,
              528526.53559999913
            ],
            [
              379524.02159999963,
              528526.04230000265
            ],
            [
              379533.52210000157,
              528524.91760000028
            ],
            [
              379543.12600000016,
              528523.17640000209
            ],
            [
              379552.67840000056,
              528520.84640000202
            ],
            [
              379561.18310000096,
              528518.14510000311
            ],
            [
              379570.27269999962,
              528514.56039999798
            ],
            [
              379580.15910000075,
              528510.02520000376
            ],
            [
              379592.50239999965,
              528503.77900000103
            ],
            [
              379596.0393000003,
              528501.81499999948
            ],
            [
              379599.88669999968,
              528499.43420000188
            ],
            [
              379612.45749999955,
              528490.87820000201
            ],
            [
              379617.22259999998,
              528487.81140000373
            ],
            [
              379622.09080000129,
              528485.04810000211
            ],
            [
              379626.63719999976,
              528482.9188000001
            ],
            [
              379634.02550000139,
              528480.24720000289
            ],
            [
              379642.45390000008,
              528477.94150000066
            ],
            [
              379651.8981999997,
              528475.95739999972
            ],
            [
              379666.46120000165,
              528473.43690000102
            ],
            [
              379676.03490000125,
              528472.08710000105
            ],
            [
              379698.69969999976,
              528469.64420000277
            ],
            [
              379708.16920000128,
              528468.23100000061
            ],
            [
              379734.47259999998,
              528463.72589999996
            ],
            [
              379742.59120000154,
              528462.67510000244
            ],
            [
              379749.90199999977,
              528462.05870000087
            ],
            [
              379757.48060000129,
              528461.85799999908
            ],
            [
              379775.74959999975,
              528462.21120000444
            ],
            [
              379784.03679999989,
              528462.05870000087
            ],
            [
              379794.60800000187,
              528461.40790000185
            ],
            [
              379803.81969999988,
              528460.58860000223
            ],
            [
              379812.25160000194,
              528459.54880000278
            ],
            [
              379820.0680000009,
              528458.26589999907
            ],
            [
              379828.42889999971,
              528456.41560000181
            ],
            [
              379837.64960000105,
              528453.81350000016
            ],
            [
              379845.85880000144,
              528451.15139999986
            ],
            [
              379869.37390000094,
              528443.0949000027
            ],
            [
              379875.87330000009,
              528440.86790000275
            ],
            [
              379896.36660000123,
              528433.37910000235
            ],
            [
              379903.0915000001,
              528431.31370000169
            ],
            [
              379909.19790000003,
              528429.82019999996
            ],
            [
              379914.37170000002,
              528428.8769000005
            ],
            [
              379920.20520000067,
              528428.0818000026
            ],
            [
              379941.43630000204,
              528426.02739999816
            ],
            [
              379966.87490000017,
              528423.47289999947
            ],
            [
              379977.46760000102,
              528422.23470000178
            ],
            [
              379999.86890000105,
              528419.2893000003
            ],
            [
              380007.08320000023,
              528418.00470000133
            ],
            [
              380013.49880000204,
              528416.54550000094
            ],
            [
              380020.88930000085,
              528414.26470000111
            ],
            [
              380037.93030000106,
              528407.69810000062
            ],
            [
              380045.73730000015,
              528405.16730000079
            ],
            [
              380051.41050000023,
              528403.78340000287
            ],
            [
              380057.78969999962,
              528402.54440000094
            ],
            [
              380080.43320000079,
              528399.18860000186
            ],
            [
              380089.35400000121,
              528397.58170000277
            ],
            [
              380095.425400001,
              528396.15220000222
            ],
            [
              380111.95210000128,
              528391.76989999972
            ],
            [
              380117.01540000085,
              528390.70000000112
            ],
            [
              380121.59250000026,
              528389.99620000087
            ],
            [
              380125.5895999996,
              528389.65170000307
            ],
            [
              380130.01760000084,
              528389.53890000284
            ],
            [
              380149.15740000084,
              528390.25049999915
            ],
            [
              380153.63250000123,
              528390.22780000046
            ],
            [
              380157.62370000035,
              528389.99620000087
            ],
            [
              380168.27130000107,
              528388.79610000364
            ],
            [
              380178.49129999988,
              528387.12590000033
            ],
            [
              380188.22890000138,
              528384.99480000138
            ],
            [
              380197.4477000013,
              528382.41070000269
            ],
            [
              380201.82280000113,
              528380.83910000138
            ],
            [
              380206.60410000011,
              528378.73210000247
            ],
            [
              380221.41089999955,
              528371.05900000036
            ],
            [
              380226.4477000013,
              528368.62949999981
            ],
            [
              380231.0792000005,
              528366.7257000003
            ],
            [
              380235.37530000042,
              528365.3433000017
            ],
            [
              380240.86170000024,
              528364.07990000024
            ],
            [
              380246.69560000021,
              528363.1895999983
            ],
            [
              380252.93739999924,
              528362.66270000115
            ],
            [
              380259.7089999998,
              528362.48850000091
            ],
            [
              380271.78790000081,
              528362.90589999966
            ],
            [
              380295.69159999955,
              528364.80550000072
            ],
            [
              380305.54130000155,
              528365.3433000017
            ],
            [
              380322.11950000003,
              528366.03810000047
            ],
            [
              380343.46889999975,
              528367.23960000277
            ],
            [
              380351.45409999974,
              528367.51649999991
            ],
            [
              380369.60479999986,
              528367.6184000019
            ],
            [
              380377.60039999988,
              528367.97929999977
            ],
            [
              380382.37349999882,
              528368.44190000184
            ],
            [
              380386.75849999953,
              528369.09669999965
            ],
            [
              380390.84330000076,
              528369.95710000023
            ],
            [
              380394.67119999975,
              528371.0324000027
            ],
            [
              380399.98950000014,
              528373.09770000167
            ],
            [
              380405.67560000066,
              528376.02920000069
            ],
            [
              380411.22060000058,
              528379.42860000208
            ],
            [
              380425.86280000024,
              528389.09950000234
            ],
            [
              380430.35529999994,
              528391.71310000308
            ],
            [
              380434.49520000163,
              528393.7890000008
            ],
            [
              380437.78939999919,
              528395.15300000273
            ],
            [
              380441.57440000027,
              528396.45180000179
            ],
            [
              380455.45689999871,
              528400.33450000174
            ],
            [
              380460.87100000121,
              528402.09759999998
            ],
            [
              380466.16440000013,
              528404.39389999956
            ],
            [
              380470.52639999986,
              528407.06360000186
            ],
            [
              380473.38150000013,
              528409.41929999925
            ],
            [
              380476.31180000026,
              528412.38690000027
            ],
            [
              380485.63280000072,
              528423.75500000082
            ],
            [
              380489.49020000082,
              528427.92380000465
            ],
            [
              380498.95029999968,
              528436.90530000255
            ],
            [
              380506.26160000078,
              528443.2378000021
            ],
            [
              380513.17520000134,
              528448.4375
            ],
            [
              380519.83229999896,
              528452.57680000179
            ],
            [
              380526.07300000079,
              528455.54630000144
            ],
            [
              380537.989500002,
              528460.11040000245
            ],
            [
              380542.58889999986,
              528462.05870000087
            ],
            [
              380545.31470000092,
              528463.44760000147
            ],
            [
              380548.31210000068,
              528465.23230000213
            ],
            [
              380559.99550000019,
              528473.20649999939
            ],
            [
              380564.94370000064,
              528476.18070000224
            ],
            [
              380568.90720000118,
              528477.92889999971
            ],
            [
              380573.68890000042,
              528479.02990000136
            ],
            [
              380578.80660000164,
              528478.55340000242
            ],
            [
              380582.99210000131,
              528477.01250000298
            ],
            [
              380585.99920000043,
              528475.31060000323
            ],
            [
              380591.44270000048,
              528471.37000000104
            ],
            [
              380604.34110000078,
              528460.66389999911
            ],
            [
              380607.74000000115,
              528458.2396000009
            ],
            [
              380610.85850000009,
              528456.36950000003
            ],
            [
              380625.56670000125,
              528448.31560000218
            ],
            [
              380633.67040000018,
              528444.31980000064
            ],
            [
              380637.70830000006,
              528442.61200000159
            ],
            [
              380641.53660000116,
              528441.21940000169
            ],
            [
              380645.2182,
              528440.1194000002
            ],
            [
              380648.78610000107,
              528439.30210000277
            ],
            [
              380653.36359999981,
              528438.68209999986
            ],
            [
              380658.55640000105,
              528438.48020000197
            ],
            [
              380663.63100000005,
              528438.61470000073
            ],
            [
              380676.2806000011,
              528439.32459999993
            ],
            [
              380682.92100000009,
              528439.30210000277
            ],
            [
              380690.54680000059,
              528438.76740000024
            ],
            [
              380699.04289999977,
              528437.87150000036
            ],
            [
              380730.33050000109,
              528433.6129999999
            ],
            [
              380760.90540000051,
              528429.32349999808
            ],
            [
              380768.77720000036,
              528428.4542999994
            ],
            [
              380775.84360000025,
              528427.92380000465
            ],
            [
              380784.26100000087,
              528427.76999999769
            ],
            [
              380803.3189000003,
              528428.22180000134
            ],
            [
              380811.87480000127,
              528427.92380000465
            ],
            [
              380822.06680000108,
              528426.87370000407
            ],
            [
              380832.69110000134,
              528425.26640000008
            ],
            [
              380843.79889999982,
              528423.09449999966
            ],
            [
              380855.49160000123,
              528420.33830000088
            ],
            [
              380859.2323000012,
              528419.24720000103
            ],
            [
              380863.35080000106,
              528417.7731999997
            ],
            [
              380877.87530000135,
              528411.64100000262
            ],
            [
              380883.70480000135,
              528409.45519999973
            ],
            [
              380889.78760000225,
              528407.79080000147
            ],
            [
              380893.95920000039,
              528407.18860000186
            ],
            [
              380898.22860000096,
              528407.0239000041
            ],
            [
              380901.28839999996,
              528407.19760000147
            ],
            [
              380908.01170000061,
              528408.19730000198
            ],
            [
              380913.55179999955,
              528409.47409999929
            ],
            [
              380927.08800000139,
              528413.18840000033
            ],
            [
              380933.24320000038,
              528414.64919999801
            ],
            [
              380957.47050000075,
              528420.34840000048
            ],
            [
              380963.67950000055,
              528421.50870000012
            ],
            [
              380969.27440000139,
              528422.23470000178
            ],
            [
              380976.55760000087,
              528422.74920000136
            ],
            [
              380984.29229999986,
              528422.92019999959
            ],
            [
              380992.55190000031,
              528422.74980000407
            ],
            [
              381001.51289999951,
              528422.23470000178
            ],
            [
              381007.36770000029,
              528421.66130000167
            ],
            [
              381013.88250000123,
              528420.74679999985
            ],
            [
              381037.54410000052,
              528416.54550000094
            ],
            [
              381059.40740000084,
              528413.05140000209
            ],
            [
              381071.67890000064,
              528410.85640000179
            ],
            [
              381091.53550000116,
              528406.81960000098
            ],
            [
              381099.02440000046,
              528405.06250000186
            ],
            [
              381105.81379999965,
              528403.27089999989
            ],
            [
              381117.99820000213,
              528399.72340000235
            ],
            [
              381127.59460000042,
              528396.58940000273
            ],
            [
              381136.10879999958,
              528393.37600000016
            ],
            [
              381143.74140000064,
              528389.99620000087
            ],
            [
              381149.50679999962,
              528387.03370000049
            ],
            [
              381155.71100000106,
              528383.4739000015
            ],
            [
              381162.40790000092,
              528379.30949999765
            ],
            [
              381172.18710000068,
              528372.92879999988
            ],
            [
              381183.61350000184,
              528365.57660000212
            ],
            [
              381189.20749999955,
              528361.76530000195
            ],
            [
              381194.39950000215,
              528357.81220000237
            ],
            [
              381198.73640000075,
              528353.96500000171
            ],
            [
              381201.3422000017,
              528351.222000001
            ],
            [
              381203.82620000094,
              528348.15630000085
            ],
            [
              381206.21350000147,
              528344.7378000021
            ],
            [
              381208.54760000017,
              528340.90420000255
            ],
            [
              381212.57650000136,
              528333.13529999927
            ],
            [
              381219.48550000135,
              528317.94370000064
            ],
            [
              381222.41079999879,
              528311.91370000131
            ],
            [
              381225.72219999973,
              528305.9366999995
            ],
            [
              381229.07850000076,
              528300.86629999988
            ],
            [
              381235.70940000005,
              528290.53050000407
            ],
            [
              381238.19190000091,
              528287.07980000414
            ],
            [
              381240.45419999957,
              528284.61930000223
            ],
            [
              381243.48110000137,
              528282.33340000361
            ],
            [
              381246.87980000209,
              528281.07950000279
            ],
            [
              381251.08590000123,
              528280.753800001
            ],
            [
              381256.73759999871,
              528281.3673000019
            ],
            [
              381266.83820000105,
              528283.32760000415
            ],
            [
              381270.79880000185,
              528283.79890000261
            ],
            [
              381292.82490000129,
              528285.40690000169
            ],
            [
              381299.21100000013,
              528285.66730000265
            ],
            [
              381304.93370000087,
              528285.69529999793
            ],
            [
              381310.4056000011,
              528285.36119999923
            ],
            [
              381324.14120000042,
              528283.82349999994
            ],
            [
              381328.01430000085,
              528283.66970000044
            ],
            [
              381331.48300000001,
              528283.79890000261
            ],
            [
              381336.88930000085,
              528284.46330000274
            ],
            [
              381342.68640000094,
              528285.60789999925
            ],
            [
              381348.97090000007,
              528287.24880000018
            ],
            [
              381356.13589999918,
              528289.48809999973
            ],
            [
              381370.8077999996,
              528294.26610000245
            ],
            [
              381375.26279999968,
              528295.9868000038
            ],
            [
              381379.07059999928,
              528297.72409999929
            ],
            [
              381382.64480000082,
              528299.70999999903
            ],
            [
              381385.68070000038,
              528301.82760000043
            ],
            [
              381388.21700000018,
              528304.10420000181
            ],
            [
              381390.27080000099,
              528306.55550000072
            ],
            [
              381392.02450000029,
              528309.60070000216
            ],
            [
              381393.46470000036,
              528313.41819999926
            ],
            [
              381394.49280000012,
              528317.31019999832
            ],
            [
              381396.55159999989,
              528326.78089999966
            ],
            [
              381397.85630000103,
              528331.20839999989
            ],
            [
              381400.92750000115,
              528339.16840000078
            ],
            [
              381404.7396000009,
              528347.89550000243
            ],
            [
              381418.71650000103,
              528376.72150000185
            ],
            [
              381432.3777999999,
              528406.52819999866
            ],
            [
              381438.08389999997,
              528418.40990000218
            ],
            [
              381444.55010000058,
              528430.61690000072
            ],
            [
              381450.95499999914,
              528441.19850000367
            ],
            [
              381456.83660000004,
              528449.6491000019
            ],
            [
              381471.81510000024,
              528469.64420000277
            ],
            [
              381486.89750000183,
              528491.02430000342
            ],
            [
              381492.0083999997,
              528498.65750000067
            ],
            [
              381496.4681000011,
              528505.67540000193
            ],
            [
              381500.0270000007,
              528511.69109999947
            ],
            [
              381507.94759999961,
              528525.90410000086
            ],
            [
              381511.63910000212,
              528532.224700002
            ],
            [
              381517.17520000041,
              528540.7042999994
            ],
            [
              381531.50129999965,
              528560.98320000246
            ],
            [
              381535.15830000117,
              528566.72320000269
            ],
            [
              381538.18840000127,
              528572.04870000109
            ],
            [
              381540.96620000061,
              528577.77860000171
            ],
            [
              381546.67950000055,
              528590.9804999996
            ],
            [
              381549.56670000032,
              528596.70160000026
            ],
            [
              381555.55950000044,
              528608.6427000016
            ],
            [
              381559.11309999973,
              528614.45760000311
            ],
            [
              381562.29330000095,
              528617.91060000099
            ],
            [
              381565.61480000056,
              528619.70980000123
            ],
            [
              381569.54870000109,
              528619.96470000036
            ],
            [
              381573.11170000117,
              528619.21440000273
            ],
            [
              381577.83470000047,
              528617.37350000255
            ],
            [
              381589.50519999955,
              528611.86309999973
            ],
            [
              381593.77240000013,
              528610.35380000062
            ],
            [
              381600.17420000117,
              528608.95450000092
            ],
            [
              381611.4142000014,
              528607.12050000206
            ],
            [
              381615.94000000134,
              528606.18349999748
            ],
            [
              381627.80769999977,
              528603.83530000038
            ],
            [
              381632.64219999965,
              528602.6054999996
            ],
            [
              381636.10950000025,
              528601.29900000431
            ],
            [
              381639.79840000067,
              528599.18759999983
            ],
            [
              381643.27720000036,
              528595.64780000038
            ],
            [
              381645.647400002,
              528591.88070000149
            ],
            [
              381647.03880000114,
              528588.79200000316
            ],
            [
              381648.24980000127,
              528585.4141000025
            ],
            [
              381649.38800000027,
              528581.50600000098
            ],
            [
              381651.97119999956,
              528570.15230000019
            ],
            [
              381652.92060000077,
              528564.75500000268
            ],
            [
              381653.53379999939,
              528558.77090000361
            ],
            [
              381653.83359999955,
              528552.07010000199
            ],
            [
              381653.86760000046,
              528543.60300000012
            ],
            [
              381653.71119999979,
              528539.44099999964
            ],
            [
              381653.30030000117,
              528534.84380000271
            ],
            [
              381650.79610000178,
              528517.05819999985
            ],
            [
              381650.07490000036,
              528509.46820000187
            ],
            [
              381649.75530000031,
              528501.57120000012
            ],
            [
              381649.64900000021,
              528493.3060999997
            ],
            [
              381649.75499999989,
              528484.60460000113
            ],
            [
              381650.07490000036,
              528475.33330000192
            ],
            [
              381650.20349999983,
              528463.54019999877
            ],
            [
              381650.40029999986,
              528459.19759999961
            ],
            [
              381650.9776999997,
              528454.61590000242
            ],
            [
              381651.97119999956,
              528450.68040000089
            ],
            [
              381653.85570000112,
              528446.20869999751
            ],
            [
              381656.66119999997,
              528441.46300000325
            ],
            [
              381660.12040000036,
              528436.6948000025
            ],
            [
              381667.14230000135,
              528427.92380000465
            ],
            [
              381669.7070999993,
              528424.97360000387
            ],
            [
              381677.04040000122,
              528417.45480000414
            ],
            [
              381678.95870000124,
              528415.05540000275
            ],
            [
              381680.85709999967,
              528411.7229999993
            ],
            [
              381681.96150000021,
              528408.10670000128
            ],
            [
              381683.13960000034,
              528398.91160000116
            ],
            [
              381683.72360000107,
              528395.96230000444
            ],
            [
              381685.38980000094,
              528392.65699999779
            ],
            [
              381689.0856999997,
              528390.66760000028
            ],
            [
              381693.18840000127,
              528390.11750000156
            ],
            [
              381696.49149999861,
              528390.2248999998
            ],
            [
              381700.09390000068,
              528390.7042999994
            ],
            [
              381703.57710000128,
              528391.51530000195
            ],
            [
              381706.5941000022,
              528392.57660000026
            ],
            [
              381710.2052000016,
              528395.20820000209
            ],
            [
              381712.00339999888,
              528398.21700000018
            ],
            [
              381712.78529999964,
              528401.59360000305
            ],
            [
              381713.04540000111,
              528405.75960000418
            ],
            [
              381712.80240000132,
              528410.56400000118
            ],
            [
              381712.06900000013,
              528416.20450000092
            ],
            [
              381710.88460000046,
              528422.56739999913
            ],
            [
              381708.86270000134,
              528431.71660000086
            ],
            [
              381707.20430000126,
              528438.40719999932
            ],
            [
              381705.47120000049,
              528443.85869999975
            ],
            [
              381703.50720000174,
              528448.55950000137
            ],
            [
              381700.58299999963,
              528453.48570000194
            ],
            [
              381698.00440000091,
              528456.2800999973
            ],
            [
              381691.02240000013,
              528461.85609999858
            ],
            [
              381688.84380000178,
              528463.80530000106
            ],
            [
              381686.62409999873,
              528466.77569999918
            ],
            [
              381685.53210000042,
              528471.59290000238
            ],
            [
              381686.11620000005,
              528476.00919999927
            ],
            [
              381687.28480000049,
              528479.38670000434
            ],
            [
              381688.81740000099,
              528482.69180000201
            ],
            [
              381690.87900000066,
              528486.42970000021
            ],
            [
              381699.38080000039,
              528499.98630000465
            ],
            [
              381703.59960000031,
              528506.61250000447
            ],
            [
              381708.49509999994,
              528513.26260000095
            ],
            [
              381714.05140000023,
              528519.91460000351
            ],
            [
              381720.24090000149,
              528526.53559999913
            ],
            [
              381722.35930000059,
              528528.51339999959
            ],
            [
              381724.90110000223,
              528530.56730000116
            ],
            [
              381734.15720000025,
              528537.09940000251
            ],
            [
              381737.54490000196,
              528539.70870000124
            ],
            [
              381740.64329999965,
              528542.59710000269
            ],
            [
              381742.99750000145,
              528545.49940000102
            ],
            [
              381745.1716,
              528548.99920000136
            ],
            [
              381747.13499999978,
              528552.83090000227
            ],
            [
              381748.84449999966,
              528556.91010000184
            ],
            [
              381750.26070000138,
              528561.14299999923
            ],
            [
              381751.34960000124,
              528565.42520000413
            ],
            [
              381752.09080000035,
              528569.67280000076
            ],
            [
              381752.46950000059,
              528573.8003000021
            ],
            [
              381752.4793999996,
              528577.7378000021
            ],
            [
              381752.19500000123,
              528581.51670000143
            ],
            [
              381751.69469999988,
              528585.23300000094
            ],
            [
              381750.99290000089,
              528588.78090000339
            ],
            [
              381750.10170000046,
              528592.10170000419
            ],
            [
              381749.04060000088,
              528595.13200000115
            ],
            [
              381747.1212000018,
              528599.08030000143
            ],
            [
              381744,
              528603.2416999992
            ],
            [
              381740.65560000017,
              528605.67400000058
            ],
            [
              381738.03129999992,
              528606.96630000137
            ],
            [
              381731.82520000078,
              528609.64709999971
            ],
            [
              381728.27850000001,
              528611.67159999721
            ],
            [
              381725.40960000083,
              528614.53490000218
            ],
            [
              381723.62470000051,
              528617.98740000278
            ],
            [
              381722.66480000131,
              528621.0466999989
            ],
            [
              381721.9589999998,
              528625.75960000232
            ],
            [
              381721.89750000089,
              528631.04560000449
            ],
            [
              381722.50179999974,
              528636.85630000383
            ],
            [
              381723.75040000118,
              528642.79870000109
            ],
            [
              381725.56970000174,
              528648.51870000176
            ],
            [
              381728.50700000115,
              528654.66380000114
            ],
            [
              381731.08820000011,
              528657.97140000015
            ],
            [
              381738.10599999968,
              528664.51730000041
            ],
            [
              381740.25160000101,
              528666.71950000152
            ],
            [
              381742.41990000103,
              528669.68989999965
            ],
            [
              381744.06930000056,
              528673.28920000046
            ],
            [
              381744.82460000087,
              528676.18229999952
            ],
            [
              381745.27160000149,
              528679.36950000003
            ],
            [
              381745.41930000018,
              528682.91319999844
            ],
            [
              381745.09379999992,
              528689.09640000202
            ],
            [
              381743.43120000139,
              528702.76480000094
            ],
            [
              381742.99750000145,
              528708.58809999935
            ],
            [
              381742.25779999979,
              528725.01940000243
            ],
            [
              381741.10110000055,
              528740.82650000043
            ],
            [
              381740.26009999961,
              528746.07509999722
            ],
            [
              381737.1015999997,
              528758.47790000215
            ],
            [
              381736.12700000033,
              528763.78810000233
            ],
            [
              381736.00680000056,
              528767.76740000211
            ],
            [
              381736.91780000087,
              528772.10760000348
            ],
            [
              381739.37660000194,
              528775.93549999967
            ],
            [
              381742.30300000124,
              528778.74670000002
            ],
            [
              381744.83740000054,
              528780.59230000153
            ],
            [
              381747.76240000129,
              528782.39280000329
            ],
            [
              381751.16629999969,
              528784.21140000038
            ],
            [
              381760.06490000058,
              528788.23600000329
            ],
            [
              381764.22790000122,
              528789.68200000189
            ],
            [
              381769.06280000135,
              528790.76680000313
            ],
            [
              381773.87019999977,
              528791.46040000208
            ],
            [
              381785.99550000113,
              528792.77950000018
            ],
            [
              381792.30340000149,
              528793.92520000413
            ],
            [
              381797.76879999973,
              528795.35559999943
            ],
            [
              381803.81440000143,
              528797.16860000044
            ],
            [
              381828.33459999971,
              528805.30350000225
            ],
            [
              381850.74630000163,
              528812.16100000218
            ],
            [
              381866.2622000007,
              528816.6817000024
            ],
            [
              381902.29340000078,
              528826.16360000148
            ],
            [
              381909.83380000107,
              528828.50200000219
            ],
            [
              381928.37640000135,
              528834.69810000062
            ],
            [
              381938.32469999976,
              528837.5418999996
            ],
            [
              381942.60110000148,
              528838.8161999993
            ],
            [
              381953.36039999966,
              528842.55959999934
            ],
            [
              381959.69340000115,
              528844.08880000189
            ],
            [
              381964.23629999999,
              528844.12680000253
            ],
            [
              381967.55340000056,
              528842.46800000221
            ],
            [
              381969.39240000024,
              528839.01789999753
            ],
            [
              381970.10960000008,
              528835.38870000094
            ],
            [
              381971.0251000002,
              528826.35689999908
            ],
            [
              381971.64969999902,
              528822.52439999953
            ],
            [
              381973.34539999999,
              528818.14020000212
            ],
            [
              381977.19460000098,
              528814.52750000171
            ],
            [
              381980.81869999971,
              528812.76109999977
            ],
            [
              381983.79910000227,
              528811.82220000029
            ],
            [
              381986.93720000051,
              528811.10469999909
            ],
            [
              381990.59100000001,
              528810.49320000038
            ],
            [
              382002.80160000082,
              528809.09620000049
            ],
            [
              382008.9673000006,
              528808.53750000149
            ],
            [
              382015.46150000021,
              528808.35100000352
            ],
            [
              382022.26560000144,
              528808.53750000149
            ],
            [
              382029.35090000089,
              528809.09620000049
            ],
            [
              382037.85630000103,
              528810.24430000037
            ],
            [
              382046.13620000053,
              528811.9066999983
            ],
            [
              382054.07560000196,
              528814.06030000187
            ],
            [
              382061.5894000018,
              528816.6817000024
            ],
            [
              382066.12050000019,
              528818.72050000355
            ],
            [
              382076.04010000173,
              528824.03319999948
            ],
            [
              382080.5532000009,
              528826.16360000148
            ],
            [
              382092.05070000049,
              528831.76930000074
            ],
            [
              382097.65280000214,
              528833.91540000029
            ],
            [
              382102.58780000079,
              528833.73300000094
            ],
            [
              382104.83509999979,
              528829.89140000008
            ],
            [
              382104.97030000016,
              528826.92200000025
            ],
            [
              382104.88550000079,
              528819.27500000224
            ],
            [
              382105.69280000124,
              528814.89300000109
            ],
            [
              382108.83820000105,
              528812.68410000019
            ],
            [
              382112.8685999997,
              528813.34190000407
            ],
            [
              382116.84489999991,
              528814.79949999973
            ],
            [
              382121.26260000095,
              528817.40289999917
            ],
            [
              382124.3880000012,
              528821.16050000116
            ],
            [
              382126.23970000073,
              528825.11050000228
            ],
            [
              382127.17339999974,
              528828.1443000026
            ],
            [
              382127.99399999995,
              528831.71539999917
            ],
            [
              382129.85900000203,
              528843.23110000044
            ],
            [
              382131.47860000096,
              528853.35830000229
            ],
            [
              382131.82919999957,
              528856.89690000378
            ],
            [
              382131.94490000047,
              528860.01340000145
            ],
            [
              382131.81600000057,
              528862.93640000001
            ],
            [
              382131.10210000072,
              528866.66389999911
            ],
            [
              382129.27840000018,
              528870.62529999949
            ],
            [
              382126.24870000128,
              528873.9045000039
            ],
            [
              382123.06510000117,
              528876.26510000415
            ],
            [
              382117.59720000066,
              528879.25760000199
            ],
            [
              382107.94120000117,
              528883.44510000385
            ],
            [
              382104.41750000045,
              528884.49880000018
            ],
            [
              382093.11649999861,
              528886.7173999995
            ],
            [
              382089.27159999963,
              528888.18300000392
            ],
            [
              382085.30080000032,
              528890.64470000193
            ],
            [
              382082.49570000079,
              528892.91300000064
            ],
            [
              382079.82020000182,
              528895.47089999914
            ],
            [
              382077.36530000065,
              528898.2313000001
            ],
            [
              382075.22180000041,
              528901.08799999952
            ],
            [
              382073.43269999977,
              528903.97940000147
            ],
            [
              382072.04070000071,
              528906.83560000174
            ],
            [
              382070.73159999959,
              528911.73930000141
            ],
            [
              382070.81840000115,
              528917.08270000108
            ],
            [
              382071.59890000056,
              528921.07330000401
            ],
            [
              382074.12679999974,
              528931.04940000176
            ],
            [
              382074.86400000006,
              528936.15369999968
            ],
            [
              382075.21019999962,
              528946.53030000255
            ],
            [
              382074.6771000009,
              528956.47809999995
            ],
            [
              382073.80860000104,
              528960.86459999904
            ],
            [
              382070.71690000035,
              528970.92440000176
            ],
            [
              382069.75370000023,
              528974.65039999969
            ],
            [
              382069.18780000042,
              528978.35269999877
            ],
            [
              382069.17489999998,
              528981.66680000164
            ],
            [
              382069.55250000022,
              528984.72790000215
            ],
            [
              382067.30580000021,
              528992.36760000326
            ],
            [
              382064.34830000065,
              528999.74360000342
            ],
            [
              382075.81350000016,
              529025.5373999998
            ],
            [
              382080.87249999959,
              529043.8142000027
            ],
            [
              382086.19790000096,
              529056.15249999985
            ],
            [
              382094.18630000018,
              529075.57900000177
            ],
            [
              382104.07030000072,
              529099.33050000109
            ],
            [
              382114.07140000071,
              529111.46710000001
            ],
            [
              382120.63830000069,
              529128.35950000212
            ],
            [
              382122.87940000091,
              529136.53440000303
            ],
            [
              382114.24250000063,
              529137.77229999937
            ],
            [
              382110.13599999994,
              529138.96210000105
            ],
            [
              382103.91880000103,
              529141.71670000069
            ],
            [
              382099.80979999993,
              529143.0364000015
            ],
            [
              382090.57150000054,
              529144.25880000368
            ],
            [
              382087.60470000003,
              529145.44019999914
            ],
            [
              382084.48080000002,
              529148.4868999999
            ],
            [
              382082.37380000111,
              529151.95250000246
            ],
            [
              382080.89390000049,
              529155.83530000225
            ],
            [
              382079.81600000057,
              529163.22460000217
            ],
            [
              382077.82450000104,
              529169.62930000201
            ],
            [
              382075.29679999966,
              529170.93009999953
            ],
            [
              382069.17489999998,
              529164.34160000272
            ],
            [
              382063.20969999954,
              529158.37399999984
            ],
            [
              382060.46240000054,
              529156.16670000181
            ],
            [
              382054.56150000077,
              529152.70240000077
            ],
            [
              382051.67690000124,
              529151.74080000073
            ],
            [
              382047.79990000091,
              529151.72250000201
            ],
            [
              382038.77350000013,
              529154.74110000394
            ],
            [
              382030.7731999997,
              529157.14120000042
            ],
            [
              382023.20229999907,
              529160.19769999944
            ],
            [
              382020.37270000111,
              529161.14140000194
            ],
            [
              382017.52850000001,
              529161.56680000201
            ],
            [
              382014.11110000219,
              529161.43670000136
            ],
            [
              382010.5933000017,
              529160.89079999924
            ],
            [
              382002.00129999872,
              529159.11140000261
            ],
            [
              381997.86020000093,
              529158.70880000107
            ],
            [
              381995.01640000008,
              529159.08139999956
            ],
            [
              381992.15789999999,
              529160.60280000232
            ],
            [
              381989.82320000138,
              529163.75800000317
            ],
            [
              381987.93570000026,
              529168.03790000267
            ],
            [
              381987.07090000063,
              529171.73690000176
            ],
            [
              381986.90359999985,
              529174.62559999898
            ],
            [
              381987.07140000165,
              529177.78100000136
            ],
            [
              381987.57130000181,
              529181.14230000041
            ],
            [
              381988.58270000014,
              529184.53970000148
            ],
            [
              381991.57150000148,
              529191.5428000018
            ],
            [
              381997.17170000076,
              529207.54350000247
            ],
            [
              382001.97190000117,
              529222.74410000257
            ]
          ]
        ]
      }
    }
  ]
}